classipypi-0.0.7.dist-info/METADATA
classipypi-0.0.7.dist-info/WHEEL
classipypi-0.0.7.dist-info/entry_points.txt
classipypi-0.0.7.dist-info/licenses/LICENSE.txt
classipypi/__init__.py
classipypi/cli.py
classipypi/core/__init__.py
classipypi/core/listing.py
classipypi/core/select.py
classipypi/core/tag_trees.py
classipypi/interfaces/__init__.py
classipypi/interfaces/display.py
classipypi/interfaces/listing.py
classipypi/interfaces/select.py
classipypi-0.0.7.dist-info/RECORD
