Metadata-Version: 2.1
Name: classipypi
Version: 0.0.7
Summary: Neurosymbolic PyPI package classifier selector.
Keywords: pydantic pypi
Author-Email: Louis Maddox <louismmx@gmail.com>
License: MIT
Classifier: Development Status :: 3 - Alpha
Classifier: Intended Audience :: Developers
Classifier: Natural Language :: English
Classifier: Topic :: Software Development :: Libraries
Classifier: Framework :: Pydantic
Classifier: Framework :: Pydantic :: 2
Classifier: Programming Language :: Python
Classifier: Programming Language :: Python :: 3.10
Classifier: Programming Language :: Python :: 3.11
Project-URL: Homepage, https://github.com/lmmx/classipypi
Project-URL: Repository, https://github.com/lmmx/classipypi.git
Requires-Python: <3.12,>=3.10
Requires-Dist: pydantic>=2.4.2
Requires-Dist: defopt
Requires-Dist: trove-classifiers>=2023.10.18
Requires-Dist: tomli-w>=1.0.0
Requires-Dist: datasets>=2.14.6; extra == "outlines"
Requires-Dist: numpy>=1.26; extra == "outlines"
Requires-Dist: outlines>=0.0.9; extra == "outlines"
Requires-Dist: torch>=2.1.0; extra == "outlines"
Requires-Dist: transformers; extra == "outlines"
Provides-Extra: outlines
